<?xml version="1.0" encoding="UTF-8"?>
<rootTag>
<Award>
<AwardTitle>Contract For Operation of the Science             InformatioN Exchange (C437)</AwardTitle>
<AGENCY>NSF</AGENCY>
<AwardEffectiveDate>06/30/1967</AwardEffectiveDate>
<AwardExpirationDate>11/30/1970</AwardExpirationDate>
<AwardTotalIntnAmount>3062356.00</AwardTotalIntnAmount>
<AwardAmount>3062356</AwardAmount>
<AwardInstrument>
<Value>Contract</Value>
</AwardInstrument>
<Organization>
<Code>05020000</Code>
<Directorate>
<Abbreviation>CSE</Abbreviation>
<LongName>Direct For Computer &amp; Info Scie &amp; Enginr</LongName>
</Directorate>
<Division>
<Abbreviation>IIS</Abbreviation>
<LongName>Div Of Information &amp; Intelligent Systems</LongName>
</Division>
</Organization>
<ProgramOfficer>
<SignBlockName>  name not available</SignBlockName>
<PO_EMAI/>
<PO_PHON/>
</ProgramOfficer>
<AbstractNarration/>
<MinAmdLetterDate>06/30/1967</MinAmdLetterDate>
<MaxAmdLetterDate>09/01/1969</MaxAmdLetterDate>
<ARRAAmount/>
<TRAN_TYPE>Grant</TRAN_TYPE>
<CFDA_NUM>47.070</CFDA_NUM>
<NSF_PAR_USE_FLAG>0</NSF_PAR_USE_FLAG>
<FUND_AGCY_CODE>4900</FUND_AGCY_CODE>
<AWDG_AGCY_CODE>4900</AWDG_AGCY_CODE>
<AwardID>5900053</AwardID>
<Investigator>
<FirstName>John</FirstName>
<LastName>Ripken</LastName>
<PI_MID_INIT>F</PI_MID_INIT>
<PI_SUFX_NAME/>
<PI_FULL_NAME>John F Ripken</PI_FULL_NAME>
<EmailAddress/>
<NSF_ID>000379647</NSF_ID>
<StartDate>06/30/1967</StartDate>
<EndDate/>
<RoleCode>Principal Investigator</RoleCode>
</Investigator>
<Institution>
<Name>Smithsonian Institution</Name>
<CityName>Washington</CityName>
<ZipCode>205600000</ZipCode>
<PhoneNumber>2026337110</PhoneNumber>
<StreetAddress>1000 Jefferson DR SW</StreetAddress>
<StreetAddress2><![CDATA[Office of Sponsored Projects]]></StreetAddress2>
<CountryName>United States</CountryName>
<StateName>District of Columbia</StateName>
<StateCode>DC</StateCode>
<CONGRESSDISTRICT>08</CONGRESSDISTRICT>
<CONGRESS_DISTRICT_ORG>DC08</CONGRESS_DISTRICT_ORG>
<ORG_DUNS_NUM>089522580</ORG_DUNS_NUM>
<ORG_LGL_BUS_NAME>SMITHSONIAN INSTITUTION</ORG_LGL_BUS_NAME>
<ORG_PRNT_DUNS_NUM>161906193</ORG_PRNT_DUNS_NUM>
</Institution>
<Performance_Institution>
<Name/>
<CityName/>
<StateCode/>
<ZipCode/>
<StreetAddress/>
<CountryCode/>
<CountryName/>
<StateName/>
<CountryFlag/>
<CONGRESSDISTRICT/>
<CONGRESS_DISTRICT_PERF>""</CONGRESS_DISTRICT_PERF>
</Performance_Institution>
<ProgramElement>
<Code>0000</Code>
<Text/>
</ProgramElement>
<FUND_OBLG>1967~364130</FUND_OBLG>
</Award>
</rootTag>
